pzen/__init__.py
pzen/audiofile_utils.py
pzen/cache_utils.py
pzen/core_types.py
pzen/lazy_utils.py
pzen/mpl_utils.py
pzen/numpy_utils.py
pzen/py.typed
pzen/signal_utils.py
pzen/torch_utils.py
pzen-0.0.6.dist-info/LICENSE
pzen-0.0.6.dist-info/WHEEL
pzen-0.0.6.dist-info/METADATA
pzen-0.0.6.dist-info/RECORD
