Metadata-Version: 2.1
Name: pzen
Version: 0.0.6
Summary: Collecting a few functions that I need in multiple projects...
Author-email: Fabian Keller <github.100.fkeller@spamgourmet.com>
Classifier: License :: OSI Approved :: MIT License
